{
    "top_center_lidar-to-center_camera-extrinsic": {
        "sensor_name": "top_center_lidar",
        "target_sensor_name": "center_camera",
        "device_type": "relational",
        "param_type": "extrinsic",
        "param": {
            "time_lag": 0,
            "sensor_calib": {
                "rows": 4,
                "cols": 4,
                "type": 6,
                "continuous": true,
                "data": [
                    [
                        0.0157969,
                        -0.999665,
                        -0.0204816,
                        -0.0597406
                    ],
                    [
                        0.00976468,
                        0.0206374,
                        -0.999739,
                        -0.200812
                    ],
                    [
                        0.999828,
                        0.0155928,
                        0.0100874,
                        0.118701
                    ],
                    [
                        0,
                        0,
                        0,
                        1
                    ]
                ]
            }
        }
    }
}
